deep_quant_lib-0.2.5.dist-info/licenses/LICENSE
deepquant/__init__.py
deepquant/heuristics.py
deepquant/utils.py
deepquant/calibration/__init__.py
deepquant/calibration/heston_calibrator.py
deepquant/calibration/hurst_forecaster.py
deepquant/data/__init__.py
deepquant/data/base_loader.py
deepquant/data/loader.py
deepquant/features/__init__.py
deepquant/features/signature_calculator.py
deepquant/features/signature_generator.py
deepquant/models/__init__.py
deepquant/models/batch_path_gen.py
deepquant/models/sde.py
deepquant/solvers/__init__.py
deepquant/solvers/base_solver.py
deepquant/solvers/deep_signature_solver.py
deepquant/solvers/hilbert_operator_solver.py
deepquant/solvers/kernel_rff_solver.py
deepquant/solvers/linear_solver.py
deepquant/workflows/__init__.py
deepquant/workflows/elemtary_pricing_workflow.py
deepquant/workflows/european_pricer.py
deepquant/workflows/price_deducer.py
deepquant/workflows/primal_dual_engine.py
deepquant_calibrator/__init__.py
deepquant_calibrator/api.py
deep_quant_lib-0.2.5.dist-info/METADATA
deep_quant_lib-0.2.5.dist-info/WHEEL
deep_quant_lib-0.2.5.dist-info/top_level.txt
deep_quant_lib-0.2.5.dist-info/RECORD
