Metadata-Version: 2.4
Name: deep-quant-lib
Version: 0.2.5
Summary: A signature-based primal-dual engine for pricing American options.
Home-page: https://github.com/c0rmac/deep-quant
Author: Cormac Kinsella
Author-email: cormac.c.00@gmail.com
License: MIT
Classifier: Programming Language :: Python :: 3
Classifier: License :: OSI Approved :: MIT License
Classifier: Operating System :: OS Independent
Classifier: Intended Audience :: Financial and Insurance Industry
Classifier: Topic :: Scientific/Engineering :: Mathematics
Requires-Python: >=3.9
License-File: LICENSE
Requires-Dist: numpy
Requires-Dist: iisignature
Requires-Dist: scikit-learn
Requires-Dist: yfinance
Requires-Dist: pandas
Requires-Dist: pandas_market_calendars
Requires-Dist: joblib
Requires-Dist: xgboost
Requires-Dist: scipy
Dynamic: license-file
